sqlalchemy_risingwave/__init__.py
sqlalchemy_risingwave/base.py
sqlalchemy_risingwave/psycopg2.py
sqlalchemy_risingwave/requirements.py
sqlalchemy_risingwave-1.4.1.dist-info/licenses/LICENSE
sqlalchemy_risingwave-1.4.1.dist-info/METADATA
sqlalchemy_risingwave-1.4.1.dist-info/WHEEL
sqlalchemy_risingwave-1.4.1.dist-info/entry_points.txt
sqlalchemy_risingwave-1.4.1.dist-info/top_level.txt
sqlalchemy_risingwave-1.4.1.dist-info/RECORD
