Metadata-Version: 2.4
Name: sqlalchemy-risingwave
Version: 1.4.1
Summary: RisingWave dialect for SQLAlchemy
Home-page: https://github.com/risingwavelabs/risingwave
Author: RisingWave Labs
Author-email: risingwave@dev.com
License: http://www.apache.org/licenses/LICENSE-2.0
Project-URL: Source, https://github.com/risingwavelabs/sqlalchemy-risingwave
Project-URL: Tracker, https://github.com/risingwavelabs/sqlalchemy-risingwave/issues
Keywords: SQLAlchemy RisingWave
Classifier: License :: OSI Approved :: Apache Software License
Classifier: Programming Language :: Python :: 3
Classifier: Programming Language :: Python :: 3 :: Only
Classifier: Programming Language :: Python :: 3.8
Classifier: Programming Language :: Python :: 3.9
Classifier: Programming Language :: Python :: 3.10
Classifier: Programming Language :: Python :: 3.11
Classifier: Programming Language :: Python :: 3.12
License-File: LICENSE
Requires-Dist: SQLAlchemy<2.0,>=1.4
Dynamic: author
Dynamic: author-email
Dynamic: classifier
Dynamic: description
Dynamic: description-content-type
Dynamic: home-page
Dynamic: keywords
Dynamic: license
Dynamic: license-file
Dynamic: project-url
Dynamic: requires-dist
Dynamic: summary
